tianhuieval/__init__.py
tianhuieval/captioning.py
tianhuieval/classification.py
tianhuieval/const.py
tianhuieval/detection.py
tianhuieval/detection_obb.py
tianhuieval/disaster.py
tianhuieval/evaluation.py
tianhuieval/retrieval.py
tianhuieval/segmentation.py
tianhuieval/visualization_tool.py
tianhuieval/vqa.py
tianhuieval-0.1.3.dist-info/METADATA
tianhuieval-0.1.3.dist-info/WHEEL
tianhuieval-0.1.3.dist-info/top_level.txt
tianhuieval-0.1.3.dist-info/RECORD
