Metadata-Version: 2.1
Name: tianhuieval
Version: 0.1.3
Summary: Tianhui evaluation tool
Author-email: Titinunt Kitrungrotsakul <titinunt121@hotmail.com>
License: MIT
Classifier: Programming Language :: Python :: 3
Classifier: License :: OSI Approved :: MIT License
Requires-Python: >=3.7
